README.md
setup.py
robot_eye_display/LCD_1inch28.py
robot_eye_display/RobotEyeDisplay.py
robot_eye_display/__init__.py
robot_eye_display/lcdconfig.py
robot_eye_display.egg-info/PKG-INFO
robot_eye_display.egg-info/SOURCES.txt
robot_eye_display.egg-info/dependency_links.txt
robot_eye_display.egg-info/top_level.txt